superlake/__init__.py
superlake/core/__init__.py
superlake/core/catalog.py
superlake/core/dataframe.py
superlake/core/delta.py
superlake/core/orchestration.py
superlake/core/pipeline.py
superlake/core/spark.py
superlake/monitoring/__init__.py
superlake/monitoring/alerts.py
superlake/monitoring/logger.py
superlake/monitoring/metrics.py
superlake/utils/__init__.py
superlake/utils/modeling.py
superlake-1.0.3.dist-info/licenses/LICENSE
superlake-1.0.3.dist-info/METADATA
superlake-1.0.3.dist-info/WHEEL
superlake-1.0.3.dist-info/top_level.txt
superlake-1.0.3.dist-info/RECORD
