Metadata-Version: 2.4
Name: superlake
Version: 1.0.3
Summary: A modern, intuitive Python package for data lakehouse operations
Home-page: https://github.com/loicmagnien/superlake
Author: Loïc Magnien
Author-email: loic.magnien@gmail.com
Classifier: Development Status :: 3 - Alpha
Classifier: Intended Audience :: Developers
Classifier: License :: OSI Approved :: MIT License
Classifier: Programming Language :: Python :: 3
Classifier: Programming Language :: Python :: 3.7
Classifier: Programming Language :: Python :: 3.8
Classifier: Programming Language :: Python :: 3.9
Requires-Python: >=3.7
License-File: LICENSE
Requires-Dist: pyspark>=3.5.0
Requires-Dist: delta-spark>=3.1.0
Requires-Dist: pandas>=1.0.0
Requires-Dist: pytz
Requires-Dist: applicationinsights
Requires-Dist: loguru
Requires-Dist: mypy
Requires-Dist: pytest
Dynamic: author
Dynamic: author-email
Dynamic: classifier
Dynamic: description
Dynamic: description-content-type
Dynamic: home-page
Dynamic: license-file
Dynamic: requires-dist
Dynamic: requires-python
Dynamic: summary
